prokbert/ProkBERTDataCollator.py
prokbert/__init__.py
prokbert/config_utils.py
prokbert/general_utils.py
prokbert/prok_datasets.py
prokbert/prokbert_tokenizer.py
prokbert/sequtils.py
prokbert/training_utils.py
prokbert/configs/pretraining.yaml
prokbert/configs/sequence_processing.yaml
prokbert/data/preprocessed/pretraining.h5
prokbert/data/preprocessed/pretraininge.h5
prokbert/data/prokbert_vocabs/prokbert-base-dna1/vocab.txt
prokbert/data/prokbert_vocabs/prokbert-base-dna2/vocab.txt
prokbert/data/prokbert_vocabs/prokbert-base-dna3/vocab.txt
prokbert/data/prokbert_vocabs/prokbert-base-dna4/vocab.txt
prokbert/data/prokbert_vocabs/prokbert-base-dna5/vocab.txt
prokbert/data/prokbert_vocabs/prokbert-base-dna6/vocab.txt
prokbert/data/prokbert_vocabs/prokbert-base-dna7/vocab.txt
prokbert/data/prokbert_vocabs/prokbert-base-dna8/vocab.txt
prokbert/data/prokbert_vocabs/prokbert-base-dna9/vocab.txt
prokbert/data/sample_data/ESKAPE_sample.fasta
prokbert/data/sample_data/pretraining/ESKAPE_sample00.fasta.gz
prokbert/data/sample_data/pretraining/ESKAPE_sample01.fasta.gz
prokbert/data/sample_data/pretraining/ESKAPE_sample02.fasta.gz
prokbert/data/sample_data/pretraining/ESKAPE_sample03.fasta.gz
prokbert/data/sample_data/pretraining/ESKAPE_sample04.fasta.gz
prokbert/data/sample_data/pretraining/ESKAPE_sample05.fasta.gz
prokbert/data/sample_data/pretraining/ESKAPE_sample06.fasta.gz
prokbert/data/sample_data/pretraining/ESKAPE_sample07.fasta.gz
prokbert/data/sample_data/pretraining/ESKAPE_sample08.fasta.gz
prokbert/data/sample_data/pretraining/ESKAPE_sample09.fasta.gz
prokbert/data/sample_data/pretraining/ESKAPE_sample10.fasta.gz
prokbert/tests/__init__.py
prokbert/tests/test_configutils.py
prokbert/tests/test_general_utils.py
prokbert/tests/test_prokBERTDataCollator.py
prokbert/tests/test_prok_datasets.py
prokbert/tests/test_prokbert_tokenizer.py
prokbert/tests/test_sequtils.py
prokbert-0.1.0.dist-info/LICENSE
prokbert-0.1.0.dist-info/METADATA
prokbert-0.1.0.dist-info/WHEEL
prokbert-0.1.0.dist-info/top_level.txt
prokbert-0.1.0.dist-info/RECORD
