Metadata-Version: 2.1
Name: prokbert
Version: 0.1.0
Summary: ProkBERT
Author-email: nbrg-ppcu <obalasz@gmail.com>
Project-URL: Homepage, https://github.com/nbrg-ppcu/prokbert
Project-URL: Bug Tracker, https://github.com/nbrg-ppcu/prokbert/issues
Classifier: Programming Language :: Python :: 3
Classifier: License :: OSI Approved :: MIT License
Classifier: Operating System :: OS Independent
Requires-Python: >=3.7
License-File: LICENSE
Requires-Dist: transformers >=4.23
Requires-Dist: biopython >=1.79
Requires-Dist: pandas >=2.0.0
Requires-Dist: h5py >=3.9.0
Requires-Dist: torch >=2.0.0
Requires-Dist: torchvision >=0.15.0
Requires-Dist: datasets >2.0.1
Requires-Dist: scikit-learn >=1.2.2
Requires-Dist: scipy >=1.10.1
Requires-Dist: tables >=3.8.0
Requires-Dist: accelerate >=0.20.1
